mimey-0.1.3.dist-info/METADATA
mimey-0.1.3.dist-info/WHEEL
mimey/__init__.py
mimey/mimey.cpython-312-darwin.so
mimey-0.1.3.dist-info/RECORD
