Metadata-Version: 2.4
Name: mimey
Version: 0.1.3
Classifier: Programming Language :: Rust
Classifier: Programming Language :: Python :: Implementation :: CPython
Classifier: Programming Language :: Python :: Implementation :: PyPy
Summary: A fast and efficient MIME type and file extension detector implemented in Rust, exposed as a Python package.
Keywords: MIME,file type detection,Rust,Python
Home-Page: https://github.com/4thel00z/mimey
License-Expression: MIT
Requires-Python: >=3.8
